hyperford/PyBorg/pyborg/__init__.py
hyperford/PyBorg/pyborg/borg.py
hyperford/model/model_functions.py
hyperford/optimise/Borg_MO_Optimisation.py
hyperford/optimise/DE_Single_Optimisation.py
hyperford/optimise/MO_energy_function.py
hyperford/optimise/PostProcessor.py
hyperford/optimise/Run_Borg_main.py
hyperford/optimise/Run_SingleDE_main.py
hyperford/optimise/opt_energy_functions.py
hyperford/optimise/pymoo_MO_Optimisation.py
hyperford/simulate/Run_Simulation.py
hyperford/simulate/sim_energy_functions.py
hyperford/utils/globalpars_JSON.py
hyperford/utils/parameters_check.py
hyper_ford-0.0.2.dist-info/METADATA
hyper_ford-0.0.2.dist-info/WHEEL
hyper_ford-0.0.2.dist-info/entry_points.txt
hyper_ford-0.0.2.dist-info/top_level.txt
hyper_ford-0.0.2.dist-info/RECORD
