Metadata-Version: 2.1
Name: hyper-ford
Version: 0.0.2
Summary: HYdroPowER Simulation and Optimization Toolbox
Author-email: Veysel Yildiz <vyildiz1@sheffield.ac.uk>
License: MIT License
Keywords: hydropower,optimization,simulation,toolbox
Requires-Python: >=3.9
Requires-Dist: numpy
Requires-Dist: platypus-opt
Requires-Dist: scipy
Requires-Dist: pandas
Requires-Dist: matplotlib
Requires-Dist: pymoo
